[
  {
    "arguments": [
      "/usr/lib64/ccache/gcc",
      "-fPIC",
      "-ansi",
      "-I../include",
      "-Wall",
      "-DLINUX",
      "-D_GNU_SOURCE",
      "-c",
      "db.c"
    ],
    "directory": "/home/zp001/MyRepos/cpp_notes/apue.3e/db",
    "file": "/home/zp001/MyRepos/cpp_notes/apue.3e/db/db.c"
  },
  {
    "arguments": [
      "/usr/bin/gcc",
      "-fPIC",
      "-ansi",
      "-Wall",
      "-I../include",
      "-DLINUX",
      "-D_GNU_SOURCE",
      "-c",
      "-fdiagnostics-color",
      "-o",
      "db.o",
      "db.c"
    ],
    "directory": "/home/zp001/MyRepos/cpp_notes/apue.3e/db",
    "file": "/home/zp001/MyRepos/cpp_notes/apue.3e/db/db.c",
    "output": "/home/zp001/MyRepos/cpp_notes/apue.3e/db/db.o"
  }
]
